fastermodels/__init__.py
fastermodels/_modidx.py
fastermodels/hf.py
fastermodels-0.0.1.dist-info/LICENSE
fastermodels-0.0.1.dist-info/METADATA
fastermodels-0.0.1.dist-info/WHEEL
fastermodels-0.0.1.dist-info/entry_points.txt
fastermodels-0.0.1.dist-info/top_level.txt
fastermodels-0.0.1.dist-info/RECORD
